expr_simplifier/__init__.py
expr_simplifier/__main__.py
expr_simplifier/py.typed
expr_simplifier/symbol_table.py
expr_simplifier/typing.py
expr_simplifier/utils.py
expr_simplifier/transforms/__init__.py
expr_simplifier/transforms/auto_simplify.py
expr_simplifier/transforms/constant_folding.py
expr_simplifier/transforms/cse.py
expr_simplifier/transforms/inline_named_expr.py
expr_simplifier/transforms/logical_simplification.py
expr_simplifier/transforms/remove_unused_named_expr.py
expr_simplifier-0.1.1.dist-info/METADATA
expr_simplifier-0.1.1.dist-info/WHEEL
expr_simplifier-0.1.1.dist-info/entry_points.txt
expr_simplifier-0.1.1.dist-info/licenses/LICENSE
expr_simplifier-0.1.1.dist-info/RECORD
