Metadata-Version: 2.3
Name: expr-simplifier
Version: 0.1.1
Project-URL: Homepage, https://github.com/ShigureLab/expr-simplifier
Project-URL: Documentation, https://github.com/ShigureLab/expr-simplifier
Project-URL: Repository, https://github.com/ShigureLab/expr-simplifier
Project-URL: Issues, https://github.com/ShigureLab/expr-simplifier/issues
Author-email: Nyakku Shigure <sigure.qaq@gmail.com>
License: MIT
License-File: LICENSE
Classifier: License :: OSI Approved :: MIT License
Classifier: Operating System :: OS Independent
Classifier: Programming Language :: Python
Classifier: Programming Language :: Python :: 3
Classifier: Programming Language :: Python :: 3.9
Classifier: Programming Language :: Python :: 3.10
Classifier: Programming Language :: Python :: 3.11
Classifier: Programming Language :: Python :: 3.12
Classifier: Programming Language :: Python :: 3.13
Classifier: Programming Language :: Python :: Implementation :: CPython
Requires-Python: >=3.9
Requires-Dist: typing-extensions>=4.12.2
